aiopppp/__init__.py
aiopppp/__main__.py
aiopppp/__version__.py
aiopppp/const.py
aiopppp/device.py
aiopppp/discover.py
aiopppp/encrypt.py
aiopppp/exceptions.py
aiopppp/http_server.py
aiopppp/packets.py
aiopppp/session.py
aiopppp/types.py
aiopppp/utils.py
aiopppp-0.2.3.dist-info/licenses/LICENSE
aiopppp-0.2.3.dist-info/METADATA
aiopppp-0.2.3.dist-info/WHEEL
aiopppp-0.2.3.dist-info/top_level.txt
aiopppp-0.2.3.dist-info/RECORD
