Metadata-Version: 2.4
Name: aiopppp
Version: 0.2.3
Summary: An asynchronous Python library for connecting to PPPP-enabled cameras.
Author-email: Ivan Belokobylskiy <belokobylskij@gmail.com>
License-Expression: Apache-2.0
Project-URL: Homepage, https://github.com/devbis/aiopppp
Project-URL: Bug Tracker, https://github.com/devbis/aiopppp/issues
Keywords: pppp,camera,async,video,streaming
Classifier: Development Status :: 4 - Beta
Classifier: Programming Language :: Python
Classifier: Programming Language :: Python :: 3
Classifier: Programming Language :: Python :: 3.7
Classifier: Programming Language :: Python :: 3.8
Classifier: Programming Language :: Python :: 3.9
Classifier: Programming Language :: Python :: 3.10
Classifier: Programming Language :: Python :: 3.11
Classifier: Programming Language :: Python :: 3.12
Classifier: Programming Language :: Python :: 3.13
Classifier: Operating System :: OS Independent
Requires-Python: >=3.7
License-File: LICENSE
Requires-Dist: aiohttp
Dynamic: license-file
